stk_data/__init__.py
stk_data/data_handling/__init__.py
stk_data/data_handling/readDat.py
stk_data/data_handling/writeDat.py
stk_data/drawing/__init__.py
stk_data/drawing/inkscapeDrawing.py
stk_data/drawing/svgLayout.py
stk_data/drawing/svg_stack.py
stk_data/plotting/__init__.py
stk_data/plotting/plot1D.py
stk_data/plotting/plot2D.py
stk_data/research/__init__.py
stk_data/research/research_header.py
stk_data/scripts/__init__.py
stk_data/scripts/getSkyrmionShapeScript.py
stk_data/statistics/__init__.py
stk_data/statistics/getSkyrmionShape.py
stk_data/statistics/statistic.py
stk_data/utils/__init__.py
stk_data/utils/util.py
stk_data-0.0.2.dist-info/LICENSE
stk_data-0.0.2.dist-info/METADATA
stk_data-0.0.2.dist-info/WHEEL
stk_data-0.0.2.dist-info/entry_points.txt
stk_data-0.0.2.dist-info/top_level.txt
stk_data-0.0.2.dist-info/RECORD
