Metadata-Version: 2.1
Name: stk_data
Version: 0.0.2
Summary: This is a library of functions for manipulating data.
Author-email: Wen Tan <2634918190@qq.com>
Project-URL: Homepage, https://github.com/sijintech/stk.git
Project-URL: Issues, https://github.com/sijintech/stk/issues/
Classifier: Programming Language :: Python :: 3
Classifier: License :: OSI Approved :: MIT License
Classifier: Operating System :: POSIX :: Linux
Requires-Python: >=3.6
License-File: LICENSE
Requires-Dist: numpy >=1.20.0
Requires-Dist: toml >=0.8.2
Requires-Dist: pandas
Requires-Dist: lxml
Requires-Dist: svgwrite
Requires-Dist: svgutils
Requires-Dist: pillow
Requires-Dist: cairosvg
Requires-Dist: matplotlib
Requires-Dist: h5py
Requires-Dist: argparse
